sphinx_rigado_theme/__init__.py
sphinx_rigado_theme/globaltoc.html
sphinx_rigado_theme/layout.html
sphinx_rigado_theme/localtoc.html
sphinx_rigado_theme/page.html
sphinx_rigado_theme/searchbar.html
sphinx_rigado_theme/sourcelink.html
sphinx_rigado_theme/theme.conf
sphinx_rigado_theme/static/css/rigado.css
sphinx_rigado_theme/static/images/favicon.ico
sphinx_rigado_theme/static/images/favicon.png
sphinx_rigado_theme/static/images/logo.png
sphinx_rigado_theme-0.0.13.dist-info/METADATA
sphinx_rigado_theme-0.0.13.dist-info/RECORD
sphinx_rigado_theme-0.0.13.dist-info/WHEEL
sphinx_rigado_theme-0.0.13.dist-info/entry_points.txt
sphinx_rigado_theme-0.0.13.dist-info/top_level.txt
